{
  "name": "association",
  "description": "",
  "primary_keys": [
    "from_id",
    "to_id",
    "type_id"
  ],
  "fields": [
    {
      "name": "from_id",
      "description": "",
      "base_type": "STRING"
    },
    {
      "name": "to_id",
      "description": "",
      "base_type": "STRING"
    },
    {
      "name": "from_object_type",
      "description": "",
      "base_type": "STRING"
    },
    {
      "name": "to_object_type",
      "description": "",
      "base_type": "STRING"
    },
        {
      "name": "category",
      "description": "",
      "base_type": "STRING"
    },
        {
      "name": "label",
      "description": "",
      "base_type": "STRING"
    },
        {
      "name": "type_id",
      "description": "",
      "base_type": "STRING"
    }
  ]
}